setup.py
mdx_anchors_away/__init__.py
mdx_anchors_away.egg-info/PKG-INFO
mdx_anchors_away.egg-info/SOURCES.txt
mdx_anchors_away.egg-info/dependency_links.txt
mdx_anchors_away.egg-info/requires.txt
mdx_anchors_away.egg-info/top_level.txt