Metadata-Version: 1.1
Name: mdx-anchors-away
Version: 1.0.1
Summary: Add anchor tags and icons to all headers
Home-page: https://github.com/marcoceppi/mdx_anchors_away
Author: Marco Ceppi
Author-email: marco@ceppi.net
License: UNKNOWN
Platform: UNKNOWN
Classifier: Environment :: Web Environment
Classifier: Intended Audience :: Developers
Classifier: Operating System :: OS Independent
Classifier: Programming Language :: Python
